optimizely_cli/__init__.py
optimizely_cli/auth.py
optimizely_cli/local_store.py
optimizely_cli/main.py
optimizely_cli/repo.py
optimizely_cli/stored_entity.py
optimizely_cli/version.py
optimizely_cli/api/__init__.py
optimizely_cli/api/client.py
optimizely_cli/api/constants.py
optimizely_cli/api/tools.py
optimizely_cli/commands/__init__.py
optimizely_cli/commands/attribute.py
optimizely_cli/commands/audience.py
optimizely_cli/commands/environment.py
optimizely_cli/commands/event.py
optimizely_cli/commands/experiment.py
optimizely_cli/commands/feature.py
optimizely_cli/commands/group.py
optimizely_cli/commands/init.py
optimizely_cli/commands/project.py
optimizely_cli/commands/pull.py
optimizely_cli/commands/push.py
optimizely_cli-0.3.0.dist-info/METADATA
optimizely_cli-0.3.0.dist-info/RECORD
optimizely_cli-0.3.0.dist-info/WHEEL
optimizely_cli-0.3.0.dist-info/entry_points.txt
optimizely_cli-0.3.0.dist-info/top_level.txt
optimizely_cli-0.3.0.dist-info/zip-safe
