Metadata-Version: 2.1
Name: optimizely-cli
Version: 0.3.0
Summary: A command-line interface for Optimizely Projects
Home-page: https://github.com/optimizely/optimizely-cli
Author: Optimizely
Author-email: developers@optimizely.com
License: Apache License 2.0
Platform: UNKNOWN
Requires-Dist: click (==6.7)
Requires-Dist: requests[security] (>=2.9.1)
Requires-Dist: findup (==0.3.0)
Requires-Dist: six (==1.11.0)
Requires-Dist: bravado (==9.2.0)
